canonicalwebteam/__init__.py
canonicalwebteam/http/__init__.py
canonicalwebteam/http/heuristics.py
tests/__init__.py
tests/test_cache.py
tests/test_heuristics.py
canonicalwebteam.http-1.0.4.dist-info/METADATA
canonicalwebteam.http-1.0.4.dist-info/WHEEL
canonicalwebteam.http-1.0.4.dist-info/top_level.txt
canonicalwebteam.http-1.0.4.dist-info/RECORD
