Metadata-Version: 2.1
Name: canonicalwebteam.http
Version: 1.0.4
Summary: For making HTTP requests with helpful defaults for Canonical's webteam.
Home-page: https://github.com/canonical-webteam/http
Author: Canonical webteam
Author-email: webteam@canonical.com
License: UNKNOWN
Platform: UNKNOWN
Requires-Dist: CacheControl[filecache] (>=0.12.5)
Requires-Dist: HTTPretty (>=1.0.2)
Requires-Dist: freezegun (>=0.3.11)
Requires-Dist: lockfile (>=0.12.2)
Requires-Dist: mockredispy (>=2.9.3)
Requires-Dist: redis (>=3.0.1)
Requires-Dist: requests (>=2.21.0)
